virgil/__init__.py
virgil/__main__.py
virgil/cli.py
virgil/config.py
virgil/commands/__init__.py
virgil/commands/config.py
virgil/commands/list.py
virgil/core/__init__.py
virgil/core/color.py
virgil/core/models.py
virgil/core/printer.py
virgil/parsers/__init__.py
virgil/parsers/base.py
virgil/parsers/pip.py
virgil-0.0.5.dist-info/LICENSE
virgil-0.0.5.dist-info/METADATA
virgil-0.0.5.dist-info/WHEEL
virgil-0.0.5.dist-info/entry_points.txt
virgil-0.0.5.dist-info/top_level.txt
virgil-0.0.5.dist-info/RECORD
