Metadata-Version: 2.1
Name: virgil
Version: 0.0.5
Summary: Virgil is a dependency management library
Home-page: https://github.com/QuicksilverMachine/virgil
Author: Dejan Knezevic
Author-email: quicksilver.machine@gmail.com
License: UNKNOWN
Project-URL: Tracker, https://github.com/QuicksilverMachine/virgil/issues
Project-URL: Documentation, https://github.com/QuicksilverMachine/virgil
Project-URL: Source, https://github.com/QuicksilverMachine/virgil
Platform: UNKNOWN
Classifier: License :: OSI Approved :: Apache Software License
Classifier: Operating System :: OS Independent
Classifier: Programming Language :: Python
Classifier: Programming Language :: Python :: 3
Classifier: Topic :: Software Development
Classifier: Topic :: Software Development :: Libraries :: Python Modules
Requires-Python: >=3.7
License-File: LICENSE
Requires-Dist: importlib-metadata (==4.8.1) ; python_version < "3.9"
